sync_model/__about__.py
sync_model/__init__.py
sync_model/admin.py
sync_model/apps.py
sync_model/exceptions.py
sync_model/models.py
sync_model/py.typed
sync_model/tests.py
sync_model/types.py
sync_model/utils.py
sync_model/views.py
sync_model/management/__init__.py
sync_model/management/commands/__init__.py
sync_model/management/commands/sync_model.py
sync_model/migrations/0001_initial.py
sync_model/migrations/0002_synctask_source_db_synctask_target_db.py
sync_model/migrations/0003_synctask_name.py
sync_model/migrations/0004_stockaction_stock_number.py
sync_model/migrations/0005_stockaction_sender.py
sync_model/migrations/0006_stockaction_update_datetime.py
sync_model/migrations/0007_broker_rawstockaction_broker.py
sync_model/migrations/__init__.py
django_sync_model-0.7.0.dist-info/METADATA
django_sync_model-0.7.0.dist-info/WHEEL
django_sync_model-0.7.0.dist-info/licenses/LICENSE
django_sync_model-0.7.0.dist-info/RECORD
